{
  "Arusha": ["Arusha City", "Arumeru", "Karatu", "Longido", "Meru", "Monduli", "Ngorongoro"],
  "Dar es Salaam": ["Ilala", "Kinondoni", "Temeke", "Ubungo", "Kigamboni"],
  "Dodoma": ["Dodoma Urban", "Bahi", "Chemba", "Chamwino", "Kondoa", "Kongwa", "Mpwapwa"],
  "Geita": ["Bukombe", "Chato", "Geita", "Mbogwe", "Nyang'hwale"],
  "Iringa": ["Iringa Urban", "Iringa Rural", "Kilolo", "Mafinga", "Mufindi"],
  "Kagera": ["Bukoba Urban", "Bukoba Rural", "Biharamulo", "Karagwe", "Kyerwa", "Muleba", "Ngara", "Missenyi"],
  "Katavi": ["Mpanda Urban", "Mpanda Rural", "Mlele"],
  "Kigoma": ["Kigoma Urban", "Kigoma Rural", "Buhigwe", "Kakonko", "Kasulu", "Kibondo", "Uvinza"],
  "Kilimanjaro": ["Moshi Urban", "Moshi Rural", "Hai", "Same", "Mwanga", "Rombo", "Siha"],
  "Lindi": ["Lindi Urban", "Lindi Rural", "Kilwa", "Liwale", "Nachingwea", "Ruangwa"],
  "Manyara": ["Babati", "Hanang", "Kiteto", "Mbulu", "Simanjiro"],
  "Mara": ["Musoma Urban", "Musoma Rural", "Bunda", "Butiama", "Rorya", "Serengeti", "Tarime"],
  "Mbeya": ["Mbeya City", "Mbeya Rural", "Chunya", "Kyela", "Mbarali", "Rungwe", "Busokelo"],
  "Morogoro": ["Morogoro Urban", "Morogoro Rural", "Gairo", "Kilombero", "Kilosa", "Mlimba", "Ulanga", "Ifakara"],
  "Mtwara": ["Mtwara Urban", "Mtwara Rural", "Masasi", "Nanyumbu", "Newala", "Tandahimba"],
  "Mwanza": ["Ilemela", "Nyamagana", "Kwimba", "Magu", "Misungwi", "Sengerema", "Ukerewe"],
  "Njombe": ["Njombe Urban", "Njombe Rural", "Ludewa", "Makambako", "Makete", "Wanging'ombe"],
  "Pwani": ["Kibaha", "Bagamoyo", "Kisarawe", "Mkuranga", "Rufiji", "Mafia", "Chalinze", "Kibiti"],
  "Rukwa": ["Sumbawanga Urban", "Sumbawanga Rural", "Kalambo", "Nkasi"],
  "Ruvuma": ["Songea Urban", "Songea Rural", "Mbinga", "Namtumbo", "Nyasa", "Tunduru"],
  "Shinyanga": ["Shinyanga Urban", "Shinyanga Rural", "Kahama", "Kishapu", "Ushetu", "Msalala"],
  "Simiyu": ["Bariadi", "Busega", "Itilima", "Maswa", "Meatu"],
  "Singida": ["Singida Urban", "Singida Rural", "Ikungi", "Iramba", "Manyoni", "Mkalama"],
  "Songwe": ["Ileje", "Mbozi", "Momba", "Songwe", "Tunduma"],
  "Tabora": ["Tabora Urban", "Igunga", "Kaliua", "Nzega", "Sikonge", "Urambo"],
  "Tanga": ["Tanga City", "Handeni", "Kilindi", "Korogwe", "Lushoto", "Mkinga", "Muheza", "Pangani"],
  "Zanzibar Urban/West": ["Magharibi A", "Magharibi B", "Mjini"],
  "Zanzibar North": ["Kaskazini A", "Kaskazini B"],
  "Zanzibar South/Pemba": ["Kusini Unguja", "Kusini Pemba", "Kati Unguja"],
  "Pemba": ["Wete", "Micheweni", "Chake Chake", "Mkoani"]
}
